{
	"Argentina": "Pearman, M. and N. Areta.  28 November 2020.",
	"Aruba": "S. Mlodinow.  6 March 2020.",
	"Bolivia": "S. Herzog.  2 June 2020.",
	"Bonaire": "E. C. Newton.  14 July 2015.",
	"Brazil": "Pacheco, J. F. and C. E. Q. Agne.  25 August 2021.",
	"Chile": "Jaramillo, A. and R. Barros.  31 December 2020.",
	"Colombia": "Asociación Colombiana de Ornitología checklist committee.  16&nbsp;February&nbsp;2018.",
	"Curaçao": "E. C. Newton.  14 July 2015.",
	"Ecuador": "Freile, J. F., et al. &nbsp;25&nbsp;August&nbsp;2021.",
	"Falklands": "R. Woods and S. Imberti.  23 June 2021.",
	"French Guiana": "O. Claessens.  1 April 2017.",
	"Guyana": "M. S. Robbins.  10 June 2013.",
	"Paraguay": "H. Del Castillo, R. Clay, A. Lesterhuis and P. Smith. &nbsp;2&nbsp;September&nbsp;2015.",
	"Peru": "M. A. Plenge, T. S. Schulenberg, and T. Valqui. &nbsp;3&nbsp;August&nbsp;2020.",
	"South America": "Remsen, et al. &nbsp;4&nbsp;October&nbsp;2021. A <a href='citations.html' target='_blank'>classification</a> of the bird species of South America. American Ornithological Society.",
	"Suriname": "O. Ottema, J. H. Ribot, and A. Spaans. &nbsp;26&nbsp;April&nbsp;2021.",
	"Trinidad": "M. Kenefick.  22 September 2020.",
	"Uruguay": "S. Claramunt and J. Aldabe.  24 August 2021.",
	"Venezuela": "D. Ascanio, C. A. Marantz, J. Miranda, J. Kvarnbäck, G. Rodriguez, J. G. León, and A. Nagy. &nbsp;18&nbsp;August&nbsp;2021."
}